{"raid":{"name":"Kuma","need_ban":false,"location":{"resource_objects":{"index":97,"items":{"0":{"description_id":"pine_tree","item":{"amount":0}},"1":{"description_id":"pine_tree","item":{"amount":0}},"2":{"description_id":"pine_tree","item":{"amount":0}},"3":{"description_id":"pine_tree","item":{"amount":0}},"4":{"description_id":"pine_tree","item":{"amount":0}},"5":{"description_id":"pine_tree","item":{"amount":0}},"6":{"description_id":"pine_tree","item":{"amount":0}},"7":{"description_id":"pine_tree","item":{"amount":0}},"8":{"description_id":"pine_tree","item":{"amount":0}},"9":{"description_id":"pine_tree","item":{"amount":0}},"10":{"description_id":"pine_tree","item":{"amount":0}},"11":{"description_id":"pine_tree","item":{"amount":0}},"12":{"description_id":"pine_tree","item":{"amount":0}},"13":{"description_id":"pine_tree","item":{"amount":0}},"14":{"description_id":"pine_tree","item":{"amount":0}},"15":{"description_id":"pine_tree","item":{"amount":0}},"16":{"description_id":"pine_tree","item":{"amount":0}},"17":{"description_id":"pine_tree","item":{"amount":0}},"18":{"description_id":"pine_tree","item":{"amount":0}},"19":{"description_id":"pine_tree","item":{"amount":0}},"20":{"description_id":"iron","item":{"amount":0}},"21":{"description_id":"iron","item":{"amount":0}},"22":{"description_id":"iron","item":{"amount":0}},"23":{"description_id":"iron","item":{"amount":0}},"24":{"description_id":"iron","item":{"amount":0}},"25":{"description_id":"rock","item":{"amount":0}},"26":{"description_id":"rock","item":{"amount":0}},"27":{"description_id":"rock","item":{"amount":0}},"28":{"description_id":"rock","item":{"amount":0}},"29":{"description_id":"rock","item":{"amount":0}},"30":{"description_id":"tree_item","item":{"amount":0}},"31":{"description_id":"tree_item","item":{"amount":0}},"32":{"description_id":"tree_item","item":{"amount":0}},"33":{"description_id":"tree_item","item":{"amount":0}},"34":{"description_id":"tree_item","item":{"amount":0}},"35":{"description_id":"tree_item","item":{"amount":0}},"36":{"description_id":"tree_item","item":{"amount":0}},"37":{"description_id":"tree_item","item":{"amount":0}},"38":{"description_id":"tree_item","item":{"amount":0}},"39":{"description_id":"tree_item","item":{"amount":0}},"40":{"description_id":"tree_item","item":{"amount":0}},"41":{"description_id":"tree_item","item":{"amount":0}},"42":{"description_id":"tree_item","item":{"amount":0}},"43":{"description_id":"tree_item","item":{"amount":0}},"44":{"description_id":"tree_item","item":{"amount":0}},"45":{"description_id":"tree_item","item":{"amount":0}},"46":{"description_id":"tree_item","item":{"amount":0}},"47":{"description_id":"tree_item","item":{"amount":0}},"48":{"description_id":"tree_item","item":{"amount":0}},"49":{"description_id":"tree_item","item":{"amount":0}},"50":{"description_id":"rock_item","item":{"amount":0}},"51":{"description_id":"rock_item","item":{"amount":0}},"52":{"description_id":"rock_item","item":{"amount":0}},"53":{"description_id":"rock_item","item":{"amount":0}},"54":{"description_id":"rock_item","item":{"amount":0}},"55":{"description_id":"rock_item","item":{"amount":0}},"56":{"description_id":"rock_item","item":{"amount":0}},"57":{"description_id":"rock_item","item":{"amount":0}},"58":{"description_id":"rock_item","item":{"amount":0}},"59":{"description_id":"rock_item","item":{"amount":0}},"60":{"description_id":"rock_item","item":{"amount":0}},"61":{"description_id":"rock_item","item":{"amount":0}},"62":{"description_id":"rock_item","item":{"amount":0}},"63":{"description_id":"rock_item","item":{"amount":0}},"64":{"description_id":"rock_item","item":{"amount":0}},"65":{"description_id":"rock_item","item":{"amount":0}},"66":{"description_id":"rock_item","item":{"amount":0}},"67":{"description_id":"rock_item","item":{"amount":0}},"68":{"description_id":"rock_item","item":{"amount":0}},"69":{"description_id":"rock_item","item":{"amount":0}},"70":{"description_id":"fiber","item":{"amount":0}},"71":{"description_id":"fiber","item":{"amount":0}},"72":{"description_id":"fiber","item":{"amount":0}},"73":{"description_id":"fiber","item":{"amount":0}},"74":{"description_id":"fiber","item":{"amount":0}},"75":{"description_id":"fiber","item":{"amount":0}},"76":{"description_id":"fiber","item":{"amount":0}},"77":{"description_id":"fiber","item":{"amount":0}},"78":{"description_id":"fiber","item":{"amount":0}},"79":{"description_id":"fiber","item":{"amount":0}},"80":{"description_id":"fiber","item":{"amount":0}},"81":{"description_id":"fiber","item":{"amount":0}},"82":{"description_id":"fiber","item":{"amount":0}},"83":{"description_id":"fiber","item":{"amount":0}},"84":{"description_id":"fiber","item":{"amount":0}},"85":{"description_id":"fiber","item":{"amount":0}},"86":{"description_id":"fiber","item":{"amount":0}},"87":{"description_id":"fiber","item":{"amount":0}},"88":{"description_id":"fiber","item":{"amount":0}},"89":{"description_id":"fiber","item":{"amount":0}},"90":{"description_id":"berry","item":{"amount":0}},"91":{"description_id":"berry","item":{"amount":0}},"92":{"description_id":"berry","item":{"amount":0}},"93":{"description_id":"berry","item":{"amount":0}},"94":{"description_id":"berry","item":{"amount":0}},"95":{"description_id":"berry","item":{"amount":0}},"96":{"description_id":"berry","item":{"amount":0}}}},"drag_box_objects":{"index":0,"items":{}},"loot_objects":{"index":1,"items":{"0":{"description_id":"chest_home_enemy","item":{"unlocked":true,"inventories":{"0":{"id":"backpack_8","inventory":{"cells":{"0":{"stack_id":"carrot","stack":{"amount":20}},"1":{"stack_id":"carrot","stack":{"amount":12}},"2":{"stack_id":"full_bottle","stack":{"amount":13}}}}}}}}}},"builder":{"foundaments":{"index":281,"items":{"149":{"description_id":"default","building":{"x":9,"y":7,"grade":2}},"139":{"description_id":"default","building":{"x":6,"y":9,"grade":2}},"152":{"description_id":"default","building":{"x":11,"y":6,"grade":2}},"153":{"description_id":"default","building":{"x":11,"y":7,"grade":2}},"151":{"description_id":"default","building":{"x":9,"y":9,"grade":2}},"150":{"description_id":"default","building":{"x":9,"y":8,"grade":2}},"138":{"description_id":"default","building":{"x":6,"y":8,"grade":2}},"135":{"description_id":"default","building":{"x":6,"y":6,"grade":2}},"134":{"description_id":"default","building":{"x":7,"y":6,"grade":2}},"178":{"description_id":"default","building":{"x":5,"y":16,"grade":2}},"279":{"description_id":"default","building":{"x":11,"y":13,"grade":2}},"160":{"description_id":"default","building":{"x":11,"y":14,"grade":2}},"133":{"description_id":"default","building":{"x":10,"y":6,"grade":2}},"140":{"description_id":"default","building":{"x":7,"y":9,"grade":2}},"179":{"description_id":"default","building":{"x":5,"y":15,"grade":2}},"154":{"description_id":"default","building":{"x":11,"y":8,"grade":2}},"161":{"description_id":"default","building":{"x":11,"y":15,"grade":2}},"169":{"description_id":"default","building":{"x":6,"y":13,"grade":2}},"168":{"description_id":"default","building":{"x":6,"y":12,"grade":2}},"167":{"description_id":"default","building":{"x":6,"y":11,"grade":2}},"162":{"description_id":"default","building":{"x":11,"y":16,"grade":2}},"172":{"description_id":"default","building":{"x":6,"y":15,"grade":2}},"148":{"description_id":"default","building":{"x":10,"y":7,"grade":2}},"171":{"description_id":"default","building":{"x":6,"y":16,"grade":2}},"186":{"description_id":"default","building":{"x":5,"y":8,"grade":2}},"187":{"description_id":"default","building":{"x":5,"y":7,"grade":2}},"170":{"description_id":"default","building":{"x":6,"y":14,"grade":2}},"185":{"description_id":"default","building":{"x":5,"y":9,"grade":2}},"184":{"description_id":"default","building":{"x":5,"y":10,"grade":2}},"173":{"description_id":"default","building":{"x":10,"y":11,"grade":2}},"174":{"description_id":"default","building":{"x":10,"y":12,"grade":2}},"183":{"description_id":"default","building":{"x":5,"y":11,"grade":2}},"182":{"description_id":"default","building":{"x":5,"y":12,"grade":2}},"175":{"description_id":"default","building":{"x":10,"y":15,"grade":2}},"181":{"description_id":"default","building":{"x":5,"y":13,"grade":2}},"176":{"description_id":"default","building":{"x":10,"y":14,"grade":2}},"136":{"description_id":"default","building":{"x":6,"y":7,"grade":2}},"128":{"description_id":"default","building":{"x":8,"y":9,"grade":2}},"132":{"description_id":"default","building":{"x":9,"y":6,"grade":2}},"143":{"description_id":"default","building":{"x":6,"y":10,"grade":2}},"142":{"description_id":"default","building":{"x":7,"y":10,"grade":2}},"141":{"description_id":"default","building":{"x":7,"y":8,"grade":2}},"155":{"description_id":"default","building":{"x":11,"y":9,"grade":2}},"156":{"description_id":"default","building":{"x":11,"y":10,"grade":2}},"163":{"description_id":"default","building":{"x":10,"y":16,"grade":2}},"165":{"description_id":"default","building":{"x":8,"y":16,"grade":2}},"166":{"description_id":"default","building":{"x":7,"y":16,"grade":2}},"164":{"description_id":"default","building":{"x":9,"y":16,"grade":2}},"180":{"description_id":"default","building":{"x":5,"y":14,"grade":2}},"177":{"description_id":"default","building":{"x":10,"y":13,"grade":2}},"137":{"description_id":"default","building":{"x":7,"y":7,"grade":2}},"130":{"description_id":"default","building":{"x":8,"y":7,"grade":2}},"129":{"description_id":"default","building":{"x":8,"y":10,"grade":2}},"131":{"description_id":"default","building":{"x":8,"y":6,"grade":2}},"144":{"description_id":"default","building":{"x":9,"y":10,"grade":2}},"127":{"description_id":"default","building":{"x":8,"y":8,"grade":2}},"145":{"description_id":"default","building":{"x":10,"y":10,"grade":2}},"232":{"description_id":"default","building":{"x":1,"y":16,"grade":2}},"230":{"description_id":"default","building":{"x":2,"y":15,"grade":2}},"228":{"description_id":"default","building":{"x":3,"y":16,"grade":2}},"226":{"description_id":"default","building":{"x":3,"y":15,"grade":2}},"146":{"description_id":"default","building":{"x":10,"y":9,"grade":2}},"231":{"description_id":"default","building":{"x":1,"y":15,"grade":2}},"229":{"description_id":"default","building":{"x":2,"y":16,"grade":2}},"227":{"description_id":"default","building":{"x":4,"y":16,"grade":2}},"225":{"description_id":"default","building":{"x":4,"y":15,"grade":2}},"224":{"description_id":"default","building":{"x":4,"y":14,"grade":2}},"223":{"description_id":"default","building":{"x":3,"y":14,"grade":2}},"221":{"description_id":"default","building":{"x":1,"y":14,"grade":2}},"222":{"description_id":"default","building":{"x":2,"y":14,"grade":2}},"147":{"description_id":"default","building":{"x":10,"y":8,"grade":2}},"220":{"description_id":"default","building":{"x":1,"y":13,"grade":2}},"218":{"description_id":"default","building":{"x":1,"y":11,"grade":2}},"216":{"description_id":"default","building":{"x":3,"y":13,"grade":2}},"219":{"description_id":"default","building":{"x":1,"y":12,"grade":2}},"217":{"description_id":"default","building":{"x":4,"y":13,"grade":2}},"215":{"description_id":"default","building":{"x":2,"y":13,"grade":2}},"214":{"description_id":"default","building":{"x":2,"y":12,"grade":2}},"213":{"description_id":"default","building":{"x":2,"y":11,"grade":2}},"212":{"description_id":"default","building":{"x":4,"y":12,"grade":2}},"209":{"description_id":"default","building":{"x":4,"y":11,"grade":2}},"210":{"description_id":"default","building":{"x":3,"y":11,"grade":2}},"207":{"description_id":"default","building":{"x":3,"y":10,"grade":2}},"208":{"description_id":"default","building":{"x":4,"y":10,"grade":2}},"211":{"description_id":"default","building":{"x":3,"y":12,"grade":2}},"189":{"description_id":"default","building":{"x":4,"y":6,"grade":2}},"190":{"description_id":"default","building":{"x":3,"y":6,"grade":2}},"191":{"description_id":"default","building":{"x":2,"y":6,"grade":2}},"188":{"description_id":"default","building":{"x":5,"y":6,"grade":2}},"206":{"description_id":"default","building":{"x":2,"y":10,"grade":2}},"205":{"description_id":"default","building":{"x":1,"y":10,"grade":2}},"204":{"description_id":"default","building":{"x":2,"y":9,"grade":2}},"203":{"description_id":"default","building":{"x":1,"y":9,"grade":2}},"192":{"description_id":"default","building":{"x":1,"y":6,"grade":2}},"193":{"description_id":"default","building":{"x":1,"y":7,"grade":2}},"194":{"description_id":"default","building":{"x":2,"y":7,"grade":2}},"195":{"description_id":"default","building":{"x":3,"y":7,"grade":2}},"196":{"description_id":"default","building":{"x":4,"y":7,"grade":2}},"197":{"description_id":"default","building":{"x":4,"y":8,"grade":2}},"202":{"description_id":"default","building":{"x":1,"y":8,"grade":2}},"201":{"description_id":"default","building":{"x":2,"y":8,"grade":2}},"200":{"description_id":"default","building":{"x":4,"y":9,"grade":2}},"199":{"description_id":"default","building":{"x":3,"y":9,"grade":2}},"198":{"description_id":"default","building":{"x":3,"y":8,"grade":2}},"233":{"description_id":"default","building":{"x":12,"y":6,"grade":2}},"234":{"description_id":"default","building":{"x":12,"y":7,"grade":2}},"235":{"description_id":"default","building":{"x":13,"y":6,"grade":2}},"236":{"description_id":"default","building":{"x":14,"y":6,"grade":2}},"237":{"description_id":"default","building":{"x":15,"y":6,"grade":2}},"238":{"description_id":"default","building":{"x":15,"y":7,"grade":2}},"239":{"description_id":"default","building":{"x":15,"y":8,"grade":2}},"240":{"description_id":"default","building":{"x":15,"y":9,"grade":2}},"241":{"description_id":"default","building":{"x":12,"y":16,"grade":2}},"242":{"description_id":"default","building":{"x":13,"y":16,"grade":2}},"243":{"description_id":"default","building":{"x":14,"y":16,"grade":2}},"280":{"description_id":"default","building":{"x":15,"y":16,"grade":2}},"245":{"description_id":"default","building":{"x":15,"y":15,"grade":2}},"246":{"description_id":"default","building":{"x":15,"y":10,"grade":2}},"247":{"description_id":"default","building":{"x":15,"y":11,"grade":2}},"248":{"description_id":"default","building":{"x":15,"y":12,"grade":2}},"249":{"description_id":"default","building":{"x":15,"y":13,"grade":2}},"250":{"description_id":"default","building":{"x":15,"y":14,"grade":2}},"251":{"description_id":"default","building":{"x":11,"y":12,"grade":2}},"252":{"description_id":"default","building":{"x":11,"y":11,"grade":2}},"253":{"description_id":"default","building":{"x":12,"y":12,"grade":2}},"254":{"description_id":"default","building":{"x":12,"y":11,"grade":2}},"255":{"description_id":"default","building":{"x":12,"y":10,"grade":2}},"256":{"description_id":"default","building":{"x":12,"y":13,"grade":2}},"257":{"description_id":"default","building":{"x":13,"y":13,"grade":2}},"258":{"description_id":"default","building":{"x":13,"y":12,"grade":2}},"259":{"description_id":"default","building":{"x":13,"y":11,"grade":2}},"260":{"description_id":"default","building":{"x":13,"y":10,"grade":2}},"261":{"description_id":"default","building":{"x":13,"y":9,"grade":2}},"262":{"description_id":"default","building":{"x":12,"y":9,"grade":2}},"263":{"description_id":"default","building":{"x":12,"y":8,"grade":2}},"264":{"description_id":"default","building":{"x":13,"y":8,"grade":2}},"265":{"description_id":"default","building":{"x":13,"y":7,"grade":2}},"266":{"description_id":"default","building":{"x":14,"y":10,"grade":2}},"267":{"description_id":"default","building":{"x":14,"y":9,"grade":2}},"268":{"description_id":"default","building":{"x":14,"y":8,"grade":2}},"269":{"description_id":"default","building":{"x":14,"y":7,"grade":2}},"270":{"description_id":"default","building":{"x":14,"y":11,"grade":2}},"271":{"description_id":"default","building":{"x":14,"y":12,"grade":2}},"272":{"description_id":"default","building":{"x":14,"y":13,"grade":2}},"273":{"description_id":"default","building":{"x":13,"y":14,"grade":2}},"274":{"description_id":"default","building":{"x":14,"y":14,"grade":2}},"275":{"description_id":"default","building":{"x":14,"y":15,"grade":2}},"276":{"description_id":"default","building":{"x":13,"y":15,"grade":2}},"277":{"description_id":"default","building":{"x":12,"y":14,"grade":2}},"278":{"description_id":"default","building":{"x":12,"y":15,"grade":2}}}},"walls":{"index":119,"items":{"26":{"description_id":"door","building":{"x":12,"y":17,"grade":2}},"27":{"description_id":"door","building":{"x":22,"y":17,"grade":2}},"28":{"description_id":"door","building":{"x":17,"y":12,"grade":2}},"29":{"description_id":"door","building":{"x":17,"y":22,"grade":2}},"31":{"description_id":"window","building":{"x":19,"y":22,"grade":2}},"32":{"description_id":"window","building":{"x":21,"y":22,"grade":2}},"33":{"description_id":"window","building":{"x":22,"y":21,"grade":2}},"34":{"description_id":"window","building":{"x":22,"y":19,"grade":2}},"35":{"description_id":"window","building":{"x":22,"y":15,"grade":2}},"36":{"description_id":"window","building":{"x":22,"y":13,"grade":2}},"37":{"description_id":"window","building":{"x":21,"y":12,"grade":2}},"38":{"description_id":"window","building":{"x":19,"y":12,"grade":2}},"39":{"description_id":"window","building":{"x":15,"y":12,"grade":2}},"40":{"description_id":"window","building":{"x":13,"y":12,"grade":2}},"41":{"description_id":"window","building":{"x":12,"y":13,"grade":2}},"42":{"description_id":"window","building":{"x":12,"y":15,"grade":2}},"43":{"description_id":"window","building":{"x":12,"y":19,"grade":2}},"44":{"description_id":"window","building":{"x":12,"y":21,"grade":2}},"45":{"description_id":"window","building":{"x":13,"y":22,"grade":2}},"46":{"description_id":"window","building":{"x":15,"y":22,"grade":2}},"47":{"description_id":"window","building":{"x":12,"y":23,"grade":2}},"48":{"description_id":"window","building":{"x":12,"y":25,"grade":2}},"49":{"description_id":"window","building":{"x":12,"y":29,"grade":2}},"50":{"description_id":"window","building":{"x":12,"y":31,"grade":2}},"51":{"description_id":"window","building":{"x":12,"y":33,"grade":2}},"52":{"description_id":"simple","building":{"x":13,"y":34,"grade":2}},"53":{"description_id":"simple","building":{"x":15,"y":34,"grade":2}},"54":{"description_id":"simple","building":{"x":17,"y":34,"grade":2}},"55":{"description_id":"simple","building":{"x":19,"y":34,"grade":2}},"56":{"description_id":"simple","building":{"x":21,"y":34,"grade":2}},"57":{"description_id":"simple","building":{"x":23,"y":34,"grade":2}},"69":{"description_id":"door","building":{"x":12,"y":27,"grade":2}},"70":{"description_id":"simple","building":{"x":11,"y":34,"grade":2}},"71":{"description_id":"simple","building":{"x":9,"y":34,"grade":2}},"72":{"description_id":"simple","building":{"x":7,"y":34,"grade":2}},"73":{"description_id":"simple","building":{"x":5,"y":34,"grade":2}},"63":{"description_id":"window","building":{"x":22,"y":23,"grade":2}},"64":{"description_id":"window","building":{"x":22,"y":25,"grade":2}},"65":{"description_id":"door","building":{"x":22,"y":27,"grade":2}},"66":{"description_id":"window","building":{"x":22,"y":29,"grade":2}},"67":{"description_id":"window","building":{"x":22,"y":31,"grade":2}},"68":{"description_id":"window","building":{"x":22,"y":33,"grade":2}},"74":{"description_id":"simple","building":{"x":3,"y":34,"grade":2}},"75":{"description_id":"simple","building":{"x":2,"y":33,"grade":2}},"76":{"description_id":"simple","building":{"x":2,"y":31,"grade":2}},"77":{"description_id":"simple","building":{"x":2,"y":29,"grade":2}},"78":{"description_id":"simple","building":{"x":2,"y":27,"grade":2}},"79":{"description_id":"simple","building":{"x":2,"y":25,"grade":2}},"80":{"description_id":"simple","building":{"x":2,"y":23,"grade":2}},"81":{"description_id":"simple","building":{"x":2,"y":21,"grade":2}},"82":{"description_id":"simple","building":{"x":2,"y":19,"grade":2}},"83":{"description_id":"simple","building":{"x":2,"y":17,"grade":2}},"84":{"description_id":"simple","building":{"x":2,"y":15,"grade":2}},"85":{"description_id":"simple","building":{"x":2,"y":13,"grade":2}},"86":{"description_id":"simple","building":{"x":3,"y":12,"grade":2}},"87":{"description_id":"simple","building":{"x":5,"y":12,"grade":2}},"88":{"description_id":"door","building":{"x":7,"y":12,"grade":2}},"89":{"description_id":"simple","building":{"x":9,"y":12,"grade":2}},"90":{"description_id":"simple","building":{"x":11,"y":12,"grade":2}},"91":{"description_id":"simple","building":{"x":11,"y":22,"grade":2}},"92":{"description_id":"simple","building":{"x":9,"y":22,"grade":2}},"93":{"description_id":"door","building":{"x":7,"y":22,"grade":2}},"94":{"description_id":"simple","building":{"x":5,"y":22,"grade":2}},"95":{"description_id":"simple","building":{"x":3,"y":22,"grade":2}},"96":{"description_id":"window","building":{"x":23,"y":12,"grade":2}},"97":{"description_id":"window","building":{"x":25,"y":12,"grade":2}},"101":{"description_id":"door","building":{"x":27,"y":12,"grade":2}},"99":{"description_id":"window","building":{"x":29,"y":12,"grade":2}},"100":{"description_id":"window","building":{"x":31,"y":12,"grade":2}},"102":{"description_id":"simple","building":{"x":32,"y":13,"grade":2}},"103":{"description_id":"simple","building":{"x":32,"y":15,"grade":2}},"104":{"description_id":"simple","building":{"x":32,"y":17,"grade":2}},"105":{"description_id":"simple","building":{"x":32,"y":19,"grade":2}},"106":{"description_id":"simple","building":{"x":32,"y":21,"grade":2}},"107":{"description_id":"simple","building":{"x":32,"y":23,"grade":2}},"108":{"description_id":"simple","building":{"x":32,"y":25,"grade":2}},"109":{"description_id":"simple","building":{"x":32,"y":27,"grade":2}},"110":{"description_id":"simple","building":{"x":32,"y":29,"grade":2}},"111":{"description_id":"simple","building":{"x":32,"y":31,"grade":2}},"117":{"description_id":"simple","building":{"x":31,"y":34,"grade":2}},"118":{"description_id":"simple","building":{"x":32,"y":33,"grade":2}},"114":{"description_id":"simple","building":{"x":29,"y":34,"grade":2}},"115":{"description_id":"simple","building":{"x":27,"y":34,"grade":2}},"116":{"description_id":"simple","building":{"x":25,"y":34,"grade":2}}}},"furnitures":{"index":49,"items":{"1":{"description_id":"workbench_gardenbed_enemy","building":{"x":12,"y":4,"rotation":0,"inventories":{"0":{"id":"enemy_workbench","inventory":{"cells":{"0":{"stack_id":"resource_seed","stack":{"amount":2}},"1":{"stack_id":"carrot","stack":{"amount":20}}}}}}}},"5":{"description_id":"workbench_watercatcher_enemy","building":{"x":7,"y":11,"rotation":0,"inventories":{"0":{"id":"enemy_workbench","inventory":{"cells":{"0":{"stack_id":"full_bottle","stack":{"amount":4}}}}}}}},"8":{"description_id":"workbench_bonfire_enemy","building":{"x":6,"y":16,"rotation":2,"inventories":{"0":{"id":"enemy_workbench","inventory":{"cells":{"0":{"stack_id":"food_carrot_stew","stack":{"amount":20}}}}}}}},"10":{"description_id":"workbench_dog_enclosure_enemy","building":{"x":7,"y":12,"rotation":0}},"37":{"description_id":"furniture_chest_8","building":{"rotation":0,"x":7,"y":10,"color_id":"default","unlocked":false,"inventories":{"0":{"id":"chest_medium","inventory":{"cells":{"0":{"stack_id":"resource_cloth","stack":{"amount":20}},"1":{"stack_id":"duct_tape","stack":{"amount":20}},"5":{"stack_id":"resource_wood_2","stack":{"amount":1}},"7":{"stack_id":"wood","stack":{"amount":20}},"11":{"stack_id":"resource_plank_2","stack":{"amount":3}},"15":{"stack_id":"resource_plank_1","stack":{"amount":20}}}}}}}},"29":{"description_id":"furniture_chest_8","building":{"rotation":0,"x":9,"y":10,"color_id":"default","unlocked":false,"inventories":{"0":{"id":"chest_medium","inventory":{"cells":{"0":{"stack_id":"microcircuit","stack":{"amount":1}},"1":{"stack_id":"resource_aluminium_wire","stack":{"amount":6}},"2":{"stack_id":"atv_wheel","stack":{}},"3":{"stack_id":"bearings","stack":{"amount":20}},"4":{"stack_id":"rubber_parts","stack":{"amount":20}},"5":{"stack_id":"paint_red","stack":{"amount":1}},"6":{"stack_id":"junk_paint","stack":{"amount":1}},"7":{"stack_id":"junk_wrench","stack":{"amount":3}},"8":{"stack_id":"paint_blue","stack":{"amount":1}},"9":{"stack_id":"truck_chainsaw","stack":{}},"10":{"stack_id":"truck_chainsaw","stack":{}},"11":{"stack_id":"resource_gasoline","stack":{"amount":2}},"12":{"stack_id":"transistor","stack":{"amount":4}},"13":{"stack_id":"wire","stack":{"amount":20}},"14":{"stack_id":"resource_rope","stack":{"amount":12}},"15":{"stack_id":"junk_cellphone","stack":{"amount":12}},"16":{"stack_id":"junk_cigarettes","stack":{"amount":1}},"17":{"stack_id":"junk_goldbar","stack":{"amount":10}},"18":{"stack_id":"junk_lightbulb","stack":{"amount":2}},"19":{"stack_id":"junk_watch","stack":{"amount":6}},"20":{"stack_id":"bunker_coupon_normal","stack":{"amount":6}},"21":{"stack_id":"bunker_coupon_easy","stack":{"amount":5}},"22":{"stack_id":"bunker_coupon_hard","stack":{"amount":3}},"23":{"stack_id":"resource_iron_plate","stack":{"amount":19}},"24":{"stack_id":"resource_thickcloth","stack":{"amount":9}}}}}}}},"17":{"description_id":"workbench_gardenbed_enemy","building":{"x":14,"y":4,"rotation":0,"inventories":{"0":{"id":"enemy_workbench","inventory":{"cells":{"0":{"stack_id":"resource_seed","stack":{"amount":2}},"1":{"stack_id":"carrot","stack":{"amount":20}}}}}}}},"19":{"description_id":"workbench_tanningrack_enemy","building":{"x":9,"y":11,"rotation":0,"inventories":{"0":{"id":"enemy_workbench","inventory":{"cells":{}}}}}},"33":{"description_id":"buildingsite_radiotable","building":{"rotation":0,"x":10,"y":10,"collection":{"completed":true,"collections":{"screws":5,"transistor":5,"resource_metalscraps":5,"duct_tape":2}}}},"35":{"description_id":"furniture_rag","building":{"rotation":0,"x":8,"y":5}},"36":{"description_id":"buildingsite_chopper","building":{"rotation":0,"x":1,"y":6,"collection":{"completed":false,"collections":{"screws":30,"bearings":10,"rubber_parts":20,"resource_metalscraps":30,"engine_parts":20,"wire":10,"chopper_wheel":2,"chopper_fork":0,"chopper_gastank":0,"backpack_8":4}}}},"38":{"description_id":"furniture_chest_8","building":{"rotation":0,"x":6,"y":10,"color_id":"default","unlocked":false,"inventories":{"0":{"id":"chest_medium","inventory":{"cells":{"0":{"stack_id":"chopper_wheel","stack":{}},"1":{"stack_id":"resource_ore_1","stack":{"amount":20}},"2":{"stack_id":"screws","stack":{"amount":18}},"3":{"stack_id":"resource_metalscraps","stack":{"amount":50}},"5":{"stack_id":"rifle_ak47","stack":{"durability":178,"slots":"30000"}},"6":{"stack_id":"rifle_m16","stack":{"durability":170,"slots":"0002"}},"7":{"stack_id":"bunker_coupon_normal","stack":{"amount":9}},"8":{"stack_id":"shotgun","stack":{"durability":40,"slots":"0000"}},"10":{"stack_id":"turret_parts","stack":{"amount":10}},"11":{"stack_id":"resource_aluminium_bar","stack":{"amount":4}},"12":{},"13":{"stack_id":"bunker_coupon_easy","stack":{"amount":11}},"15":{"stack_id":"pass_card_a","stack":{"amount":4}},"16":{"stack_id":"engine_parts","stack":{"amount":1}},"17":{"stack_id":"aid_kit","stack":{"amount":20}}}}}}}},"39":{"description_id":"workbench_sawmill_enemy","building":{"x":15,"y":6,"rotation":1,"inventories":{"0":{"id":"enemy_workbench","inventory":{"cells":{}}}}}},"40":{"description_id":"workbench_smeltery_enemy","building":{"x":15,"y":9,"rotation":1,"inventories":{"0":{"id":"enemy_workbench","inventory":{"cells":{}}}}}},"41":{"description_id":"furniture_shower","building":{"rotation":0,"x":9,"y":5}},"42":{"description_id":"workbench_stonecutter_enemy","building":{"x":14,"y":6,"rotation":1,"inventories":{"0":{"id":"enemy_workbench","inventory":{"cells":{}}}}}},"43":{"description_id":"workbench_sewingmachine_enemy","building":{"x":13,"y":6,"rotation":1,"inventories":{"0":{"id":"enemy_workbench","inventory":{"cells":{}}}}}},"44":{"description_id":"workbench_bench_enemy","building":{"x":12,"y":6,"rotation":1,"inventories":{"0":{"id":"enemy_workbench","inventory":{"cells":{}}}}}},"45":{"description_id":"workbench_medictable_enemy","building":{"x":11,"y":6,"rotation":1,"inventories":{"0":{"id":"enemy_workbench","inventory":{"cells":{}}}}}},"46":{"description_id":"workbench_recycling_enemy","building":{"x":15,"y":11,"rotation":1,"inventories":{"0":{"id":"enemy_workbench","inventory":{"cells":{}}}}}},"47":{"description_id":"buildingsite_gunsmith","building":{"rotation":1,"x":14,"y":13,"collection":{"completed":false,"collections":{"resource_bar_1":0,"duct_tape":0,"screws":0,"rubber_parts":0,"wire":0,"furniture_chest_8":0}}}},"48":{"description_id":"workbench_meatdryer_enemy","building":{"x":10,"y":16,"rotation":0,"inventories":{"0":{"id":"enemy_workbench","inventory":{"cells":{}}}}}}}},"foundation_grid":{"0":{},"1":{},"2":{},"3":{},"4":{},"5":{},"6":{"1":{"item":{"id":"default","index":"192"}},"2":{"item":{"id":"default","index":"191"}},"3":{"item":{"id":"default","index":"190"}},"4":{"item":{"id":"default","index":"189"}},"5":{"item":{"id":"default","index":"188"}},"6":{"item":{"id":"default","index":"135"}},"7":{"item":{"id":"default","index":"134"}},"8":{"item":{"id":"default","index":"131"}},"9":{"item":{"id":"default","index":"132"}},"10":{"item":{"id":"default","index":"133"}},"11":{"item":{"id":"default","index":"152"}},"12":{"item":{"id":"default","index":"233"}},"13":{"item":{"id":"default","index":"235"}},"14":{"item":{"id":"default","index":"236"}},"15":{"item":{"id":"default","index":"237"}}},"7":{"1":{"item":{"id":"default","index":"193"}},"2":{"item":{"id":"default","index":"194"}},"3":{"item":{"id":"default","index":"195"}},"4":{"item":{"id":"default","index":"196"}},"5":{"item":{"id":"default","index":"187"}},"6":{"item":{"id":"default","index":"136"}},"7":{"item":{"id":"default","index":"137"}},"8":{"item":{"id":"default","index":"130"}},"9":{"item":{"id":"default","index":"149"}},"10":{"item":{"id":"default","index":"148"}},"11":{"item":{"id":"default","index":"153"}},"12":{"item":{"id":"default","index":"234"}},"13":{"item":{"id":"default","index":"265"}},"14":{"item":{"id":"default","index":"269"}},"15":{"item":{"id":"default","index":"238"}}},"8":{"1":{"item":{"id":"default","index":"202"}},"2":{"item":{"id":"default","index":"201"}},"3":{"item":{"id":"default","index":"198"}},"4":{"item":{"id":"default","index":"197"}},"5":{"item":{"id":"default","index":"186"}},"6":{"item":{"id":"default","index":"138"}},"7":{"item":{"id":"default","index":"141"}},"8":{"item":{"id":"default","index":"127"}},"9":{"item":{"id":"default","index":"150"}},"10":{"item":{"id":"default","index":"147"}},"11":{"item":{"id":"default","index":"154"}},"12":{"item":{"id":"default","index":"263"}},"13":{"item":{"id":"default","index":"264"}},"14":{"item":{"id":"default","index":"268"}},"15":{"item":{"id":"default","index":"239"}}},"9":{"1":{"item":{"id":"default","index":"203"}},"2":{"item":{"id":"default","index":"204"}},"3":{"item":{"id":"default","index":"199"}},"4":{"item":{"id":"default","index":"200"}},"5":{"item":{"id":"default","index":"185"}},"6":{"item":{"id":"default","index":"139"}},"7":{"item":{"id":"default","index":"140"}},"8":{"item":{"id":"default","index":"128"}},"9":{"item":{"id":"default","index":"151"}},"10":{"item":{"id":"default","index":"146"}},"11":{"item":{"id":"default","index":"155"}},"12":{"item":{"id":"default","index":"262"}},"13":{"item":{"id":"default","index":"261"}},"14":{"item":{"id":"default","index":"267"}},"15":{"item":{"id":"default","index":"240"}}},"10":{"1":{"item":{"id":"default","index":"205"}},"2":{"item":{"id":"default","index":"206"}},"3":{"item":{"id":"default","index":"207"}},"4":{"item":{"id":"default","index":"208"}},"5":{"item":{"id":"default","index":"184"}},"6":{"item":{"id":"default","index":"143"}},"7":{"item":{"id":"default","index":"142"}},"8":{"item":{"id":"default","index":"129"}},"9":{"item":{"id":"default","index":"144"}},"10":{"item":{"id":"default","index":"145"}},"11":{"item":{"id":"default","index":"156"}},"12":{"item":{"id":"default","index":"255"}},"13":{"item":{"id":"default","index":"260"}},"14":{"item":{"id":"default","index":"266"}},"15":{"item":{"id":"default","index":"246"}}},"11":{"1":{"item":{"id":"default","index":"218"}},"2":{"item":{"id":"default","index":"213"}},"3":{"item":{"id":"default","index":"210"}},"4":{"item":{"id":"default","index":"209"}},"5":{"item":{"id":"default","index":"183"}},"6":{"item":{"id":"default","index":"167"}},"10":{"item":{"id":"default","index":"173"}},"11":{"item":{"id":"default","index":"252"}},"12":{"item":{"id":"default","index":"254"}},"13":{"item":{"id":"default","index":"259"}},"14":{"item":{"id":"default","index":"270"}},"15":{"item":{"id":"default","index":"247"}}},"12":{"1":{"item":{"id":"default","index":"219"}},"2":{"item":{"id":"default","index":"214"}},"3":{"item":{"id":"default","index":"211"}},"4":{"item":{"id":"default","index":"212"}},"5":{"item":{"id":"default","index":"182"}},"6":{"item":{"id":"default","index":"168"}},"10":{"item":{"id":"default","index":"174"}},"11":{"item":{"id":"default","index":"251"}},"12":{"item":{"id":"default","index":"253"}},"13":{"item":{"id":"default","index":"258"}},"14":{"item":{"id":"default","index":"271"}},"15":{"item":{"id":"default","index":"248"}}},"13":{"1":{"item":{"id":"default","index":"220"}},"2":{"item":{"id":"default","index":"215"}},"3":{"item":{"id":"default","index":"216"}},"4":{"item":{"id":"default","index":"217"}},"5":{"item":{"id":"default","index":"181"}},"6":{"item":{"id":"default","index":"169"}},"10":{"item":{"id":"default","index":"177"}},"11":{"item":{"id":"default","index":"279"}},"12":{"item":{"id":"default","index":"256"}},"13":{"item":{"id":"default","index":"257"}},"14":{"item":{"id":"default","index":"272"}},"15":{"item":{"id":"default","index":"249"}}},"14":{"1":{"item":{"id":"default","index":"221"}},"2":{"item":{"id":"default","index":"222"}},"3":{"item":{"id":"default","index":"223"}},"4":{"item":{"id":"default","index":"224"}},"5":{"item":{"id":"default","index":"180"}},"6":{"item":{"id":"default","index":"170"}},"10":{"item":{"id":"default","index":"176"}},"11":{"item":{"id":"default","index":"160"}},"12":{"item":{"id":"default","index":"277"}},"13":{"item":{"id":"default","index":"273"}},"14":{"item":{"id":"default","index":"274"}},"15":{"item":{"id":"default","index":"250"}}},"15":{"1":{"item":{"id":"default","index":"231"}},"2":{"item":{"id":"default","index":"230"}},"3":{"item":{"id":"default","index":"226"}},"4":{"item":{"id":"default","index":"225"}},"5":{"item":{"id":"default","index":"179"}},"6":{"item":{"id":"default","index":"172"}},"10":{"item":{"id":"default","index":"175"}},"11":{"item":{"id":"default","index":"161"}},"12":{"item":{"id":"default","index":"278"}},"13":{"item":{"id":"default","index":"276"}},"14":{"item":{"id":"default","index":"275"}},"15":{"item":{"id":"default","index":"245"}}},"16":{"1":{"item":{"id":"default","index":"232"}},"2":{"item":{"id":"default","index":"229"}},"3":{"item":{"id":"default","index":"228"}},"4":{"item":{"id":"default","index":"227"}},"5":{"item":{"id":"default","index":"178"}},"6":{"item":{"id":"default","index":"171"}},"7":{"item":{"id":"default","index":"166"}},"8":{"item":{"id":"default","index":"165"}},"9":{"item":{"id":"default","index":"164"}},"10":{"item":{"id":"default","index":"163"}},"11":{"item":{"id":"default","index":"162"}},"12":{"item":{"id":"default","index":"241"}},"13":{"item":{"id":"default","index":"242"}},"14":{"item":{"id":"default","index":"243"}},"15":{"item":{"id":"default","index":"280"}}},"17":{}},"wall_grid":{"0":{},"1":{},"2":{},"3":{},"4":{},"5":{},"6":{},"7":{},"8":{},"9":{},"10":{},"11":{},"12":{"3":{"item":{"id":"simple","index":"86"}},"5":{"item":{"id":"simple","index":"87"}},"7":{"item":{"id":"door","index":"88"}},"9":{"item":{"id":"simple","index":"89"}},"11":{"item":{"id":"simple","index":"90"}},"13":{"item":{"id":"window","index":"40"}},"15":{"item":{"id":"window","index":"39"}},"17":{"item":{"id":"door","index":"28"}},"19":{"item":{"id":"window","index":"38"}},"21":{"item":{"id":"window","index":"37"}},"23":{"item":{"id":"window","index":"96"}},"25":{"item":{"id":"window","index":"97"}},"27":{"item":{"id":"door","index":"101"}},"29":{"item":{"id":"window","index":"99"}},"31":{"item":{"id":"window","index":"100"}}},"13":{"2":{"item":{"id":"simple","index":"85"}},"12":{"item":{"id":"window","index":"41"}},"22":{"item":{"id":"window","index":"36"}},"32":{"item":{"id":"simple","index":"102"}}},"14":{},"15":{"2":{"item":{"id":"simple","index":"84"}},"12":{"item":{"id":"window","index":"42"}},"22":{"item":{"id":"window","index":"35"}},"32":{"item":{"id":"simple","index":"103"}}},"16":{},"17":{"2":{"item":{"id":"simple","index":"83"}},"12":{"item":{"id":"door","index":"26"}},"22":{"item":{"id":"door","index":"27"}},"32":{"item":{"id":"simple","index":"104"}}},"18":{},"19":{"2":{"item":{"id":"simple","index":"82"}},"12":{"item":{"id":"window","index":"43"}},"22":{"item":{"id":"window","index":"34"}},"32":{"item":{"id":"simple","index":"105"}}},"20":{},"21":{"2":{"item":{"id":"simple","index":"81"}},"12":{"item":{"id":"window","index":"44"}},"22":{"item":{"id":"window","index":"33"}},"32":{"item":{"id":"simple","index":"106"}}},"22":{"3":{"item":{"id":"simple","index":"95"}},"5":{"item":{"id":"simple","index":"94"}},"7":{"item":{"id":"door","index":"93"}},"9":{"item":{"id":"simple","index":"92"}},"11":{"item":{"id":"simple","index":"91"}},"13":{"item":{"id":"window","index":"45"}},"15":{"item":{"id":"window","index":"46"}},"17":{"item":{"id":"door","index":"29"}},"19":{"item":{"id":"window","index":"31"}},"21":{"item":{"id":"window","index":"32"}}},"23":{"2":{"item":{"id":"simple","index":"80"}},"12":{"item":{"id":"window","index":"47"}},"22":{"item":{"id":"window","index":"63"}},"32":{"item":{"id":"simple","index":"107"}}},"24":{},"25":{"2":{"item":{"id":"simple","index":"79"}},"12":{"item":{"id":"window","index":"48"}},"22":{"item":{"id":"window","index":"64"}},"32":{"item":{"id":"simple","index":"108"}}},"26":{},"27":{"2":{"item":{"id":"simple","index":"78"}},"12":{"item":{"id":"door","index":"69"}},"22":{"item":{"id":"door","index":"65"}},"32":{"item":{"id":"simple","index":"109"}}},"28":{},"29":{"2":{"item":{"id":"simple","index":"77"}},"12":{"item":{"id":"window","index":"49"}},"22":{"item":{"id":"window","index":"66"}},"32":{"item":{"id":"simple","index":"110"}}},"30":{},"31":{"2":{"item":{"id":"simple","index":"76"}},"12":{"item":{"id":"window","index":"50"}},"22":{"item":{"id":"window","index":"67"}},"32":{"item":{"id":"simple","index":"111"}}},"32":{},"33":{"2":{"item":{"id":"simple","index":"75"}},"12":{"item":{"id":"window","index":"51"}},"22":{"item":{"id":"window","index":"68"}},"32":{"item":{"id":"simple","index":"118"}}},"34":{"3":{"item":{"id":"simple","index":"74"}},"5":{"item":{"id":"simple","index":"73"}},"7":{"item":{"id":"simple","index":"72"}},"9":{"item":{"id":"simple","index":"71"}},"11":{"item":{"id":"simple","index":"70"}},"13":{"item":{"id":"simple","index":"52"}},"15":{"item":{"id":"simple","index":"53"}},"17":{"item":{"id":"simple","index":"54"}},"19":{"item":{"id":"simple","index":"55"}},"21":{"item":{"id":"simple","index":"56"}},"23":{"item":{"id":"simple","index":"57"}},"25":{"item":{"id":"simple","index":"116"}},"27":{"item":{"id":"simple","index":"115"}},"29":{"item":{"id":"simple","index":"114"}},"31":{"item":{"id":"simple","index":"117"}}},"35":{},"36":{}},"furniture_grid":{"0":{},"1":{},"2":{},"3":{},"4":{"12":{"item":{"id":"workbench_gardenbed","index":"1"}},"13":{"item":{"id":"workbench_gardenbed","index":"1"}},"14":{"item":{"id":"workbench_gardenbed","index":"17"}},"15":{"item":{"id":"workbench_gardenbed","index":"17"}}},"5":{"8":{"item":{"id":"furniture_rag","index":"35"}},"9":{"item":{"id":"furniture_shower","index":"41"}},"12":{"item":{"id":"workbench_gardenbed","index":"1"}},"13":{"item":{"id":"workbench_gardenbed","index":"1"}},"14":{"item":{"id":"workbench_gardenbed","index":"17"}},"15":{"item":{"id":"workbench_gardenbed","index":"17"}}},"6":{"1":{"item":{"id":"buildingsite_chopper","index":"36"}},"2":{"item":{"id":"buildingsite_chopper","index":"36"}},"11":{"item":{"id":"workbench_medictable","index":"45"}},"12":{"item":{"id":"workbench_bench","index":"44"}},"13":{"item":{"id":"workbench_sewingmachine","index":"43"}},"14":{"item":{"id":"workbench_stonecutter","index":"42"}},"15":{"item":{"id":"workbench_sawmill","index":"39"}}},"7":{"1":{"item":{"id":"buildingsite_chopper","index":"36"}},"2":{"item":{"id":"buildingsite_chopper","index":"36"}}},"8":{},"9":{"15":{"item":{"id":"workbench_smeltery","index":"40"}}},"10":{"6":{"item":{"id":"furniture_chest_8","index":"38"}},"7":{"item":{"id":"furniture_chest_8","index":"37"}},"9":{"item":{"id":"furniture_chest_8","index":"29"}},"10":{"item":{"id":"buildingsite_radiotable","index":"33"}}},"11":{"7":{"item":{"id":"workbench_watercatcher","index":"5"}},"9":{"item":{"id":"workbench_tanningrack","index":"19"}},"15":{"item":{"id":"workbench_recycling","index":"46"}}},"12":{"7":{"item":{"id":"workbench_dog_enclosure","index":"10"}},"8":{"item":{"id":"workbench_dog_enclosure","index":"10"}},"9":{"item":{"id":"workbench_dog_enclosure","index":"10"}}},"13":{"7":{"item":{"id":"workbench_dog_enclosure","index":"10"}},"8":{"item":{"id":"workbench_dog_enclosure","index":"10"}},"9":{"item":{"id":"workbench_dog_enclosure","index":"10"}},"14":{"item":{"id":"buildingsite_gunsmith","index":"47"}},"15":{"item":{"id":"buildingsite_gunsmith","index":"47"}}},"14":{"7":{"item":{"id":"workbench_dog_enclosure","index":"10"}},"8":{"item":{"id":"workbench_dog_enclosure","index":"10"}},"9":{"item":{"id":"workbench_dog_enclosure","index":"10"}},"14":{"item":{"id":"buildingsite_gunsmith","index":"47"}},"15":{"item":{"id":"buildingsite_gunsmith","index":"47"}}},"15":{"7":{"item":{"id":"workbench_dog_enclosure","index":"10"}},"8":{"item":{"id":"workbench_dog_enclosure","index":"10"}},"9":{"item":{"id":"workbench_dog_enclosure","index":"10"}}},"16":{"6":{"item":{"id":"workbench_bonfire","index":"8"}},"10":{"item":{"id":"workbench_meatdryer","index":"48"}}},"17":{}}},"characters":{"index":65,"items":{}}}}}